.DS_Store
update_wordings.py
Mobile_Text_Tool-1.1.2.dist-info/DESCRIPTION.rst
Mobile_Text_Tool-1.1.2.dist-info/METADATA
Mobile_Text_Tool-1.1.2.dist-info/RECORD
Mobile_Text_Tool-1.1.2.dist-info/WHEEL
Mobile_Text_Tool-1.1.2.dist-info/entry_points.txt
Mobile_Text_Tool-1.1.2.dist-info/metadata.json
Mobile_Text_Tool-1.1.2.dist-info/top_level.txt
mobileStrings/.DS_Store
mobileStrings/__init__.py
mobileStrings/collection_utils.py
mobileStrings/csv_unicode.py
mobileStrings/text_in.py
mobileStrings/text_out.py
