Metadata-Version: 2.0
Name: Mobile-Text-Tool
Version: 1.1.2
Summary: Tools for editing translations in mobile apps
Home-page: https://github.com/ncornette/python-mobile-text-tool
Author: Nicolas Cornette
Author-email: nicolas.cornette@gmail.com
License: MIT
Keywords: translations mobile development
Platform: UNKNOWN
Classifier: Development Status :: 5 - Production/Stable
Classifier: Intended Audience :: Developers
Classifier: Topic :: Software Development :: Build Tools
Classifier: License :: OSI Approved :: MIT License
Classifier: Programming Language :: Python :: 2.7
Requires-Dist: openpyxl
Requires-Dist: simplejson (>3.8)
